{
  "project_info": {
    "project_number": "409183344836",
    "project_id": "my-parentcare-app",
    "storage_bucket": "my-parentcare-app.firebasestorage.app"
  },
  "client": [
    {
      "client_info": {
        "mobilesdk_app_id": "1:409183344836:android:267a51011b6fd1f7229191",
        "android_client_info": {
          "package_name": "com.example.parent_care"
        }
      },
      "oauth_client": [],
      "api_key": [
        {
          "current_key": "AIzaSyCQ1uY-vodAGMXhNdsw-Xzu3pi0WfbEHP8"
        }
      ],
      "services": {
        "appinvite_service": {
          "other_platform_oauth_client": []
        }
      }
    }
  ],
  "configuration_version": "1"
}